odoo/addons/hr_personal_equipment_variant_configurator/README.rst
odoo/addons/hr_personal_equipment_variant_configurator/__init__.py
odoo/addons/hr_personal_equipment_variant_configurator/__manifest__.py
odoo/addons/hr_personal_equipment_variant_configurator/i18n/es.po
odoo/addons/hr_personal_equipment_variant_configurator/i18n/es_PA.po
odoo/addons/hr_personal_equipment_variant_configurator/i18n/hr_personal_equipment_variant_configurator.pot
odoo/addons/hr_personal_equipment_variant_configurator/i18n/it.po
odoo/addons/hr_personal_equipment_variant_configurator/models/__init__.py
odoo/addons/hr_personal_equipment_variant_configurator/models/hr_personal_equipment.py
odoo/addons/hr_personal_equipment_variant_configurator/readme/CONTRIBUTORS.rst
odoo/addons/hr_personal_equipment_variant_configurator/readme/DESCRIPTION.rst
odoo/addons/hr_personal_equipment_variant_configurator/readme/INSTALL.rst
odoo/addons/hr_personal_equipment_variant_configurator/static/description/icon.png
odoo/addons/hr_personal_equipment_variant_configurator/static/description/index.html
odoo/addons/hr_personal_equipment_variant_configurator/views/hr_personal_equipment_request.xml
odoo13_addon_hr_personal_equipment_variant_configurator-13.0.1.0.1.dev10.dist-info/METADATA
odoo13_addon_hr_personal_equipment_variant_configurator-13.0.1.0.1.dev10.dist-info/WHEEL
odoo13_addon_hr_personal_equipment_variant_configurator-13.0.1.0.1.dev10.dist-info/top_level.txt
odoo13_addon_hr_personal_equipment_variant_configurator-13.0.1.0.1.dev10.dist-info/RECORD
